nmrespy/__init__.py
nmrespy/__main__.py
nmrespy/_colors.py
nmrespy/_docstrings.py
nmrespy/_errors.py
nmrespy/_files.py
nmrespy/_freqconverter.py
nmrespy/_get_a
nmrespy/_install_to_topspin.py
nmrespy/_misc.py
nmrespy/_paths_and_links.py
nmrespy/_result_fetcher.py
nmrespy/_timing.py
nmrespy/contour_app.py
nmrespy/expinfo.py
nmrespy/freqfilter.py
nmrespy/load.py
nmrespy/mpm.py
nmrespy/nlp.py
nmrespy/plot.py
nmrespy/sig.py
nmrespy/__pycache__/__init__.cpython-311.pyc
nmrespy/__pycache__/__init__.cpython-313.pyc
nmrespy/__pycache__/_colors.cpython-311.pyc
nmrespy/__pycache__/_colors.cpython-313.pyc
nmrespy/__pycache__/_errors.cpython-311.pyc
nmrespy/__pycache__/_errors.cpython-313.pyc
nmrespy/__pycache__/_files.cpython-311.pyc
nmrespy/__pycache__/_files.cpython-313.pyc
nmrespy/__pycache__/_freqconverter.cpython-311.pyc
nmrespy/__pycache__/_freqconverter.cpython-313.pyc
nmrespy/__pycache__/_misc.cpython-311.pyc
nmrespy/__pycache__/_misc.cpython-313.pyc
nmrespy/__pycache__/_paths_and_links.cpython-311.pyc
nmrespy/__pycache__/_paths_and_links.cpython-313.pyc
nmrespy/__pycache__/_result_fetcher.cpython-311.pyc
nmrespy/__pycache__/_result_fetcher.cpython-313.pyc
nmrespy/__pycache__/_timing.cpython-311.pyc
nmrespy/__pycache__/_timing.cpython-313.pyc
nmrespy/__pycache__/contour_app.cpython-311.pyc
nmrespy/__pycache__/expinfo.cpython-311.pyc
nmrespy/__pycache__/expinfo.cpython-313.pyc
nmrespy/__pycache__/freqfilter.cpython-311.pyc
nmrespy/__pycache__/freqfilter.cpython-313.pyc
nmrespy/__pycache__/load.cpython-311.pyc
nmrespy/__pycache__/mpm.cpython-311.pyc
nmrespy/__pycache__/mpm.cpython-313.pyc
nmrespy/__pycache__/plot.cpython-311.pyc
nmrespy/__pycache__/sig.cpython-311.pyc
nmrespy/__pycache__/sig.cpython-313.pyc
nmrespy/_sanity/__init__.py
nmrespy/_sanity/funcs.py
nmrespy/_sanity/__pycache__/__init__.cpython-311.pyc
nmrespy/_sanity/__pycache__/__init__.cpython-313.pyc
nmrespy/_sanity/__pycache__/funcs.cpython-311.pyc
nmrespy/_sanity/__pycache__/funcs.cpython-313.pyc
nmrespy-2.1.0.dist-info/licenses/LICENSE
nmrespy-2.1.0.dist-info/METADATA
nmrespy-2.1.0.dist-info/WHEEL
nmrespy-2.1.0.dist-info/top_level.txt
nmrespy-2.1.0.dist-info/RECORD
