Metadata-Version: 2.4
Name: nmrespy
Version: 2.1.0
Summary: NMR-EsPy: Nuclear Magnetic Resonance Estimation in Python
Author-email: Simon Hulse <simon.hulse@chem.ox.ac.uk>
License: Copyright 2022 Simon Hulse
Project-URL: documentation, https://foroozandehgroup.github.io/NMR-EsPy/
Project-URL: github, https://github.com/foroozandehgroup/NMR-EsPy
Keywords: Estimation,NMR,Signal Processing,Optimisation
Classifier: Programming Language :: Python :: 3.8
Classifier: Programming Language :: Python :: 3.9
Classifier: Programming Language :: Python :: 3.10
Classifier: Programming Language :: Python :: 3.11
Classifier: License :: OSI Approved :: MIT License
Classifier: Operating System :: OS Independent
Classifier: Topic :: Scientific/Engineering
Requires-Python: >=3.8
License-File: LICENSE
Requires-Dist: matplotlib
Requires-Dist: numpy
Requires-Dist: scipy
Requires-Dist: bruker_utils
Requires-Dist: pybaselines
Requires-Dist: Pillow>=10.0.0
Provides-Extra: dev
Requires-Dist: pyproject-flake8; extra == "dev"
Requires-Dist: pytest; extra == "dev"
Requires-Dist: pytest-cov; extra == "dev"
Provides-Extra: docs
Requires-Dist: Sphinx; extra == "docs"
Requires-Dist: sphinx-nameko-theme; extra == "docs"
Dynamic: license-file
